falconx/__init__.py
falconx/client.py
falconx-1.0.6.dist-info/licenses/LICENSE
falconx-1.0.6.dist-info/METADATA
falconx-1.0.6.dist-info/WHEEL
falconx-1.0.6.dist-info/top_level.txt
falconx-1.0.6.dist-info/RECORD
