Metadata-Version: 2.4
Name: falconx
Version: 1.0.6
Summary: The official client for FalconX APIs
Home-page: https://github.com/falconxio/falconx-python
Author: FalconX
Author-email: support@falconx.io
Classifier: Programming Language :: Python :: 3
Classifier: License :: OSI Approved :: MIT License
Classifier: Operating System :: OS Independent
License-File: LICENSE
Dynamic: author
Dynamic: author-email
Dynamic: classifier
Dynamic: description
Dynamic: description-content-type
Dynamic: home-page
Dynamic: license-file
Dynamic: summary
